README.rst
setup.py
httpdebug/__init__.py
httpdebug.egg-info/PKG-INFO
httpdebug.egg-info/SOURCES.txt
httpdebug.egg-info/dependency_links.txt
httpdebug.egg-info/entry_points.txt
httpdebug.egg-info/requires.txt
httpdebug.egg-info/top_level.txt
httpdebug.egg-info/zip-safe